<?xml version="1.0" encoding="UTF-8"?><extraction><clueid>145955193</clueid><fullpath><![CDATA[http://www.winecompanion.com.au/wineries/south-australia/mclaren-vale/cape-barren-wines]]></fullpath><theme>WinerySearchDetailsNick1</theme><middle>default</middle><baseURI><bucketBaseURI><bucketName>WineryInfoDetails</bucketName><uri><![CDATA[http://www.winecompanion.com.au/wineries/south-australia/mclaren-vale/cape-barren-wines]]></uri></bucketBaseURI></baseURI>
<WineryInfoDetails><item><name>Cape Barren Wines</name><region>McLaren Vale</region><address1/><address2/><website>www.capebarrenwines.com</website><telephone/><winemaker/><wineryards/><facsimilie/><description/></item></WineryInfoDetails></extraction>