<?xml version="1.0" encoding="UTF-8"?><extraction><clueid>146035915</clueid><fullpath><![CDATA[http://www.winecompanion.com.au/wineries/queensland/queensland-zone/villacoola-vineyard--winery]]></fullpath><theme>WinerySearchDetailsNick1</theme><middle>default</middle><baseURI><bucketBaseURI><bucketName>WineryInfoDetails</bucketName><uri><![CDATA[http://www.winecompanion.com.au/wineries/queensland/queensland-zone/villacoola-vineyard--winery]]></uri></bucketBaseURI></baseURI>
<WineryInfoDetails><item><name>Villacoola Vineyard &amp; Winery</name><region>Queensland Zone</region><address1>
            Carnarvon Highway, Surat, Qld 4417</address1><address2>
            
            Queensland Zone
            QLD
            
        </address2><website/><telephone>
            (07) 4626 5103
        </telephone><winemaker>
            Contract
        </winemaker><wineryards>
            Not Available
        </wineryards><facsimilie>
            (07) 4626 5516
        </facsimilie><description>
            Ron Ritchie has ventured far to the west to establish Villacoola Vineyard &amp; Winery  its nearest neighbour is Romavilla (at Roma), 78km to the north. The 2.5ha vineyard is planted to sauvignon blanc, semillon, chardonnay, merlot, shiraz and muscat; the muscats provide the fortified wines for which Romavilla has been famous for 140 years.
        </description></item></WineryInfoDetails></extraction>