<?xml version="1.0" encoding="UTF-8"?><extraction><clueid>145990327</clueid><fullpath><![CDATA[http://www.winecompanion.com.au/wineries/victoria/port-phillip-zone/limbic]]></fullpath><theme>WinerySearchDetailsNick1</theme><middle>default</middle><baseURI><bucketBaseURI><bucketName>WineryInfoDetails</bucketName><uri><![CDATA[http://www.winecompanion.com.au/wineries/victoria/port-phillip-zone/limbic]]></uri></bucketBaseURI></baseURI>
<WineryInfoDetails><item><name>Limbic</name><region>Port Phillip Zone</region><address1/><address2/><website>www.limbicwines.com.au</website><telephone/><winemaker/><wineryards/><facsimilie/><description/></item></WineryInfoDetails></extraction>