<?xml version="1.0" encoding="UTF-8"?><extraction><clueid>146001743</clueid><fullpath><![CDATA[http://www.winecompanion.com.au/wineries/other/various/mt-toolleen]]></fullpath><theme>WinerySearchDetailsNick1</theme><middle>default</middle><baseURI><bucketBaseURI><bucketName>WineryInfoDetails</bucketName><uri><![CDATA[http://www.winecompanion.com.au/wineries/other/various/mt-toolleen]]></uri></bucketBaseURI></baseURI>
<WineryInfoDetails><item><name>Mt Toolleen</name><region>Various</region><address1>
            Level 12, North Tower, 459 Collins Street, Melbourne, Vic 3000 (postal)</address1><address2>
            
            Various
            SA
            
        </address2><website>www.mttoolleen.com.au</website><telephone>
            (03) 9885 1367
        </telephone><winemaker>
            Mark Jamieson (Contract)
        </winemaker><wineryards>
            Not Available
        </wineryards><facsimilie>
            (03) 9885 1367
        </facsimilie><description>
            Mt Toolleen is owned by a group of Melbourne investors in a somewhat complicated joint venture scheme that gives Mt Toolleen access to 100ha of shiraz grown in Barossa Valley, and ownership of a 17.5ha vineyard in Heathcote. Exports to Canada, China, Taiwan, United Arab Emirates and Hong Kong.
        </description></item></WineryInfoDetails></extraction>