<?xml version="1.0" encoding="UTF-8"?><extraction><clueid>146028548</clueid><fullpath><![CDATA[http://www.winecompanion.com.au/wineries/victoria/gippsland/tarwin-ridge]]></fullpath><theme>WinerySearchDetailsNick1</theme><middle>default</middle><baseURI><bucketBaseURI><bucketName>WineryInfoDetails</bucketName><uri><![CDATA[http://www.winecompanion.com.au/wineries/victoria/gippsland/tarwin-ridge]]></uri></bucketBaseURI></baseURI>
<WineryInfoDetails><item><name>Tarwin Ridge</name><region>Gippsland</region><address1>
            Wintles Road, Leongatha South, Vic 3953</address1><address2>
            
            Gippsland
            VIC
            
        </address2><website/><telephone>
            (03) 5664 3211
        </telephone><winemaker>
            Brian Anstee
        </winemaker><wineryards>
            Not Available
        </wineryards><facsimilie>
            (03) 5664 3211
        </facsimilie><description>
            Brian Anstee makes his wines at Nicholson River, under the gaze of fellow social worker Ken Eckersley. The wines come from 2ha of estate pinot and 0.5ha each of cabernet and sauvignon blanc.
        </description></item></WineryInfoDetails></extraction>