<?xml version="1.0" encoding="UTF-8"?><extraction><clueid>145956491</clueid><fullpath><![CDATA[http://www.winecompanion.com.au/wineries/queensland/granite-belt/castle-glen-vineyard]]></fullpath><theme>WinerySearchDetailsNick1</theme><middle>default</middle><baseURI><bucketBaseURI><bucketName>WineryInfoDetails</bucketName><uri><![CDATA[http://www.winecompanion.com.au/wineries/queensland/granite-belt/castle-glen-vineyard]]></uri></bucketBaseURI></baseURI>
<WineryInfoDetails><item><name>Castle Glen Vineyard</name><region>Granite Belt</region><address1>
            Amiens Road, The Summit, Qld, 4377</address1><address2>
            
            Granite Belt
            QLD
            
        </address2><website/><telephone>
            (07) 4683 2363
        </telephone><winemaker>
            Cedric Millar
        </winemaker><wineryards>
            Not Available
        </wineryards><facsimilie>
            (07) 4683 2169
        </facsimilie><description>
            Unashamedly caters for the general tourist, with a large castle boasting an open fire set in 40 ha, and specialising in 27 liqueur-style fruit wines, but with Chardonnay, Shiraz, Merlot, Cabernet Sauvignon, Semillon and White Muscat also available.
        </description></item></WineryInfoDetails></extraction>